[{"rooms": "5室2厅", "toward": "南北向", "year": "2016年建", "origin_url": "https://nn.esf.fang.com/chushou/3_161565905.htm", "unit": "9130元/㎡", "floor": "高层（共32层）", "address": "三塘-昆仑大道995号", "name": "嘉和城温莎北郡", "price": "\n\t\t\t\t\t\t\t\t\t\t\t105万", "city": "南宁", "area": "115㎡", "province": "广西"},{"rooms": "3室2厅", "toward": "南北向", "year": "2007年建", "origin_url": "https://nn.esf.fang.com/chushou/3_164070893.htm", "unit": "7543元/㎡", "floor": "中层（共11层）", "address": "东沟岭-秀厢大道103号建材家饰市场旁", "name": "澳华花园", "price": "\n\t\t\t\t\t\t\t\t\t\t\t86万", "city": "南宁", "area": "114㎡", "province": "广西"},{"rooms": "2室2厅", "toward": "南北向", "year": "2011年建", "origin_url": "https://nn.esf.fang.com/chushou/3_163944515.htm", "unit": "10013元/㎡", "floor": "中层（共28层）", "address": "朝阳广场-澳门街住宅人民东路33号", "name": "澳门街住宅", "price": "\n\t\t\t\t\t\t\t\t\t\t\t73万", "city": "南宁", "area": "72.9㎡", "province": "广西"},{"rooms": "4室2厅", "toward": "南北向", "year": "2015年建", "origin_url": "https://nn.esf.fang.com/chushou/3_164341388.htm", "unit": "12019元/㎡", "floor": "中层（共35层）", "address": "安吉片区-安阳路11号(南宁花卉公园旁)", "name": "盛天时代", "price": "\n\t\t\t\t\t\t\t\t\t\t\t125万", "city": "南宁", "area": "104㎡", "province": "广西"},{"rooms": "2室2厅", "toward": "南北向", "year": "2018年建", "origin_url": "https://nn.esf.fang.com/chushou/3_164290936.htm", "unit": "15175元/㎡", "floor": "低层（共32层）", "address": "东盟商务区-凤岭南路16号(凤岭南路与青环路交汇处)", "name": "保利领秀前城", "price": "\n\t\t\t\t\t\t\t\t\t\t\t195万", "city": "南宁", "area": "128.5㎡", "province": "广西"},{"rooms": "4室2厅", "toward": "南北向", "year": "2015年建", "origin_url": "https://nn.esf.fang.com/chushou/3_164328812.htm", "unit": "12805元/㎡", "floor": "中层（共40层）", "address": "安吉片区-发展大道以东、吉兴西路以北", "name": "大嘉汇尚悦", "price": "\n\t\t\t\t\t\t\t\t\t\t\t110万", "city": "南宁", "area": "85.9㎡", "province": "广西"},{"city": "南宁", "address": null, "price": "", "origin_url": "https://nn.esf.fang.com/", "province": "广西", "unit": null},{"rooms": "5室3厅", "toward": "南北向", "year": "2015年建", "origin_url": "https://nn.esf.fang.com/chushou/3_164341032.htm", "unit": "28481元/㎡", "floor": "低层（共47层）", "address": "白沙片区-凯旋1号", "name": "凯旋1号", "price": "\n\t\t\t\t\t\t\t\t\t\t\t900万", "city": "南宁", "area": "316㎡", "province": "广西"},{"rooms": "2室2厅", "toward": "南向", "year": "2011年建", "origin_url": "https://nn.esf.fang.com/chushou/3_164259480.htm", "unit": "16475元/㎡", "floor": "低层（共31层）", "address": "蟠龙片区-平乐大道1号", "name": "碧水天和", "price": "\n\t\t\t\t\t\t\t\t\t\t\t158万", "city": "南宁", "area": "95.9㎡", "province": "广西"},{"rooms": "3室2厅", "toward": "南北向", "year": "2004年建", "origin_url": "https://nn.esf.fang.com/chushou/3_164328881.htm", "unit": "6956元/㎡", "floor": "中层（共7层）", "address": "秀厢大道-西乡塘万秀北路243号", "name": "高秀公寓", "price": "\n\t\t\t\t\t\t\t\t\t\t\t80万", "city": "南宁", "area": "115㎡", "province": "广西"},{"rooms": "3室2厅", "toward": "南向", "year": "2014年建", "origin_url": "https://nn.esf.fang.com/chushou/3_164330461.htm", "unit": "10493元/㎡", "floor": "高层（共26层）", "address": "三塘-昆仑大道995号", "name": "嘉和城温莎北郡", "price": "\n\t\t\t\t\t\t\t\t\t\t\t87万", "city": "南宁", "area": "82.91㎡", "province": "广西"},{"rooms": "4室2厅", "toward": "北向", "year": "2014年建", "origin_url": "https://nn.esf.fang.com/chushou/3_164343639.htm", "unit": "11923元/㎡", "floor": "中层（共35层）", "address": "安吉片区-安阳路11号(南宁花卉公园旁)", "name": "盛天时代", "price": "\n\t\t\t\t\t\t\t\t\t\t\t124万", "city": "南宁", "area": "104㎡", "province": "广西"},{"rooms": "2室2厅", "toward": "南北向", "year": "2016年建", "origin_url": "https://nn.esf.fang.com/chushou/3_164337321.htm", "unit": "10526元/㎡", "floor": "低层（共33层）", "address": "兴宁东-盛天小世界昆仑大道58号(广西药用植物园旁)", "name": "盛天小世界", "price": "\n\t\t\t\t\t\t\t\t\t\t\t72万", "city": "南宁", "area": "68.4㎡", "province": "广西"},{"city": "南宁", "address": "东沟岭-兴宁邕武路20号(邕武路上3公里处", "name": "保利山渐青", "price": "\n\t\t\t\t\t\t\t\t\t\t\t500万", "toward": "南向", "origin_url": "https://nn.esf.fang.com/chushou/10_164323473.htm", "area": "215㎡", "province": "广西", "unit": "23255元/㎡"},{"rooms": "3室1厅", "toward": "南向", "year": "2006年建", "origin_url": "https://nn.esf.fang.com/chushou/3_164172449.htm", "unit": "8962元/㎡", "floor": "中层（共30层）", "address": "五一片区-富宁新兴苑", "name": "富宁新兴苑", "price": "\n\t\t\t\t\t\t\t\t\t\t\t95万", "city": "南宁", "area": "106㎡", "province": "广西"},{"rooms": "2室2厅", "toward": "南北向", "year": "2016年建", "origin_url": "https://nn.esf.fang.com/chushou/3_164306108.htm", "unit": "11000元/㎡", "floor": "低层（共33层）", "address": "国家经济开发区-那洪大道37号(那洪壮锦路口)", "name": "汇东星城", "price": "\n\t\t\t\t\t\t\t\t\t\t\t66万", "city": "南宁", "area": "60㎡", "province": "广西"},{"rooms": "3室2厅", "toward": "南向", "year": "2014年建", "origin_url": "https://nn.esf.fang.com/chushou/3_164283983.htm", "unit": "13736元/㎡", "floor": "中层（共33层）", "address": "明秀路-正恒国际广场", "name": "正恒国际广场", "price": "\n\t\t\t\t\t\t\t\t\t\t\t125万", "city": "南宁", "area": "91㎡", "province": "广西"},{"rooms": "4室2厅", "toward": "南北向", "year": "2014年建", "origin_url": "https://nn.esf.fang.com/chushou/3_164315429.htm", "unit": "10579元/㎡", "floor": "中层（共33层）", "address": "三塘-昆仑大道995号", "name": "嘉和城温莎北郡", "price": "\n\t\t\t\t\t\t\t\t\t\t\t95万", "city": "南宁", "area": "89.8㎡", "province": "广西"},{"rooms": "3室2厅", "toward": "南北向", "year": "2015年建", "origin_url": "https://nn.esf.fang.com/chushou/3_164338768.htm", "unit": "9662元/㎡", "floor": "高层（共33层）", "address": "三塘-昆仑大道995号", "name": "嘉和城依云堡", "price": "\n\t\t\t\t\t\t\t\t\t\t\t86万", "city": "南宁", "area": "89㎡", "province": "广西"},{"rooms": "3室2厅", "toward": "南向", "year": "2020年建", "origin_url": "https://nn.esf.fang.com/chushou/3_164226631.htm", "unit": "13814元/㎡", "floor": "中层（共33层）", "address": "玉洞片区-那黄大道129号", "name": "五象澜庭府", "price": "\n\t\t\t\t\t\t\t\t\t\t\t134万", "city": "南宁", "area": "97㎡", "province": "广西"},{"rooms": "3室1厅", "toward": "南北向", "year": "2013年建", "origin_url": "https://nn.esf.fang.com/chushou/3_164083747.htm", "unit": "12291元/㎡", "floor": "低层（共32层）", "address": "明秀东-荣和山水绿城明秀东路88号(明秀建材市场内)", "name": "荣和山水绿城", "price": "\n\t\t\t\t\t\t\t\t\t\t\t96万", "city": "南宁", "area": "78.1㎡", "province": "广西"},{"rooms": "4室2厅", "toward": "南北向", "year": "2014年建", "origin_url": "https://nn.esf.fang.com/chushou/3_164184415.htm", "unit": "8375元/㎡", "floor": "中层（共28层）", "address": "相思湖新区-骋望怡璟湾", "name": "骋望怡璟湾", "price": "\n\t\t\t\t\t\t\t\t\t\t\t165万", "city": "南宁", "area": "197㎡", "province": "广西"},{"rooms": "5室3厅", "toward": "南北向", "year": "2015年建", "origin_url": "https://nn.esf.fang.com/chushou/3_164335560.htm", "unit": "28481元/㎡", "floor": "低层（共45层）", "address": "白沙片区-凯旋1号", "name": "凯旋1号", "price": "\n\t\t\t\t\t\t\t\t\t\t\t900万", "city": "南宁", "area": "316㎡", "province": "广西"},{"rooms": "2室2厅", "toward": "南向", "year": "2017年建", "origin_url": "https://nn.esf.fang.com/chushou/3_164251939.htm", "unit": "11470元/㎡", "floor": "低层（共32层）", "address": "沙井片区-江南大道富德段98号(清川桥南东侧)", "name": "骋望珺玺", "price": "\n\t\t\t\t\t\t\t\t\t\t\t78万", "city": "南宁", "area": "68㎡", "province": "广西"},{"rooms": "3室2厅", "toward": "南向", "year": "2015年建", "origin_url": "https://nn.esf.fang.com/chushou/3_164065646.htm", "unit": "10786元/㎡", "floor": "低层（共34层）", "address": "国家经济开发区-那洪大道37号(那洪壮锦路口)", "name": "汇东星城", "price": "\n\t\t\t\t\t\t\t\t\t\t\t96万", "city": "南宁", "area": "89㎡", "province": "广西"},{"rooms": "3室2厅", "toward": "南北向", "year": "2015年建", "origin_url": "https://nn.esf.fang.com/chushou/3_164070495.htm", "unit": "12209元/㎡", "floor": "中层（共30层）", "address": "明秀东-明秀东路178号(原虎邱装饰材料市场)", "name": "江宇世纪城", "price": "\n\t\t\t\t\t\t\t\t\t\t\t105万", "city": "南宁", "area": "86㎡", "province": "广西"},{"rooms": "2室2厅", "toward": "南向", "year": "2001年建", "origin_url": "https://nn.esf.fang.com/chushou/3_164341411.htm", "unit": "7794元/㎡", "floor": "中层（共7层）", "address": "友爱北湖片区-唐山路50号", "name": "唐山路50号小区", "price": "\n\t\t\t\t\t\t\t\t\t\t\t53万", "city": "南宁", "area": "68㎡", "province": "广西"},{"rooms": "3室2厅", "toward": "南北向", "year": "2009年建", "origin_url": "https://nn.esf.fang.com/chushou/3_164096579.htm", "unit": "7648元/㎡", "floor": "中层（共18层）", "address": "高新开发区-高新技术开发区创新6号(富士胶卷斜对面)", "name": "A派公馆", "price": "\n\t\t\t\t\t\t\t\t\t\t\t95万", "city": "南宁", "area": "124.2㎡", "province": "广西"},{"rooms": "4室2厅", "toward": "南北向", "year": "2009年建", "origin_url": "https://nn.esf.fang.com/chushou/3_164283977.htm", "unit": "11023元/㎡", "floor": "中层（共20层）", "address": "鲁班路-康桥蓝湾鲁班路85号(广西大学西门对面)", "name": "康桥蓝湾", "price": "\n\t\t\t\t\t\t\t\t\t\t\t140万", "city": "南宁", "area": "127㎡", "province": "广西"},{"rooms": "2室2厅", "toward": "南北向", "year": "2015年建", "origin_url": "https://nn.esf.fang.com/chushou/3_164290765.htm", "unit": "17187元/㎡", "floor": "低层（共31层）", "address": "蟠龙片区-博艺路8号(南宁大桥旁)", "name": "江悦蓝湾", "price": "\n\t\t\t\t\t\t\t\t\t\t\t110万", "city": "南宁", "area": "64㎡", "province": "广西"},{"rooms": "3室2厅", "toward": "南北向", "year": "2016年建", "origin_url": "https://nn.esf.fang.com/chushou/3_163678843.htm", "unit": "20130元/㎡", "floor": "中层（共33层）", "address": "东葛片区-绿地中央广场东葛路161号(青秀万达对面 )", "name": "绿地中央广场", "price": "\n\t\t\t\t\t\t\t\t\t\t\t247万", "city": "南宁", "area": "122.7㎡", "province": "广西"},{"rooms": "3室2厅", "toward": "南北向", "year": "2020年建", "origin_url": "https://nn.esf.fang.com/chushou/3_163825510.htm", "unit": "16497元/㎡", "floor": "中层（共38层）", "address": "玉洞片区-平乐大道35号(五象湖公园旁)", "name": "宝能五象湖1号", "price": "\n\t\t\t\t\t\t\t\t\t\t\t153.18万", "city": "南宁", "area": "92.85㎡", "province": "广西"},{"rooms": "4室2厅", "toward": "南北向", "year": "2020年建", "origin_url": "https://nn.esf.fang.com/chushou/3_163825591.htm", "unit": "14565元/㎡", "floor": "中层（共32层）", "address": "玉洞片区-平乐大道35号(五象湖公园旁)", "name": "宝能五象湖1号", "price": "\n\t\t\t\t\t\t\t\t\t\t\t208万", "city": "南宁", "area": "142.8㎡", "province": "广西"},{"rooms": "4室2厅", "toward": "南北向", "year": "2018年建", "origin_url": "https://nn.esf.fang.com/chushou/3_163463030.htm", "unit": "11180元/㎡", "floor": "低层（共32层）", "address": "国家经济开发区-金阳路9号(那洪大道与金阳路交汇处)", "name": "龙光玖珑府", "price": "\n\t\t\t\t\t\t\t\t\t\t\t131万", "city": "南宁", "area": "117.17㎡", "province": "广西"},{"rooms": "3室2厅", "toward": "南北向", "year": "2005年建", "origin_url": "https://nn.esf.fang.com/chushou/3_164282467.htm", "unit": "20143元/㎡", "floor": "高层（共30层）", "address": "金湖片区-佳得鑫水晶城埌东金湖路61号(五象广场旁)", "name": "佳得鑫水晶城", "price": "\n\t\t\t\t\t\t\t\t\t\t\t280万", "city": "南宁", "area": "139㎡", "province": "广西"},{"rooms": "7室2厅", "toward": "南北向", "year": "2017年建", "origin_url": "https://nn.esf.fang.com/chushou/3_164312901.htm", "unit": "25000元/㎡", "floor": "高层（共10层）", "address": "东盟商务区-中房翡翠湾东盟商务区桂花路1号", "name": "中房翡翠湾", "price": "\n\t\t\t\t\t\t\t\t\t\t\t684.85万", "city": "南宁", "area": "273.94㎡", "province": "广西"},{"rooms": "1室1厅", "toward": "南北向", "year": "2007年建", "origin_url": "https://nn.esf.fang.com/chushou/3_164195914.htm", "unit": "7857元/㎡", "floor": "低层（共18层）", "address": "仙葫经济开发区-东方广场蓉茉大道12号", "name": "东方广场", "price": "\n\t\t\t\t\t\t\t\t\t\t\t33万", "city": "南宁", "area": "42㎡", "province": "广西"},{"rooms": "3室2厅", "toward": "南北向", "year": "2010年建", "origin_url": "https://nn.esf.fang.com/chushou/3_164308782.htm", "unit": "7272元/㎡", "floor": "中层（共6层）", "address": "东沟岭-澳华花园秀厢大道103号建材家饰市场旁", "name": "澳华花园", "price": "\n\t\t\t\t\t\t\t\t\t\t\t80万", "city": "南宁", "area": "110㎡", "province": "广西"},{"rooms": "3室2厅", "toward": "南北向", "year": "2020年建", "origin_url": "https://nn.esf.fang.com/chushou/3_164271942.htm", "unit": "14708元/㎡", "floor": "中层（共33层）", "address": "蟠龙片区-宋厢路18号(南宁艺术博物馆东畔)", "name": "盛科城", "price": "\n\t\t\t\t\t\t\t\t\t\t\t181.8万", "city": "南宁", "area": "123.6㎡", "province": "广西"},{"rooms": "4室2厅", "toward": "东南向", "year": "2014年建", "origin_url": "https://nn.esf.fang.com/chushou/3_164302258.htm", "unit": "12020元/㎡", "floor": "低层（共33层）", "address": "东沟岭-保利爱琴海南宁市秀厢大道81号", "name": "保利爱琴海", "price": "\n\t\t\t\t\t\t\t\t\t\t\t108万", "city": "南宁", "area": "89.85㎡", "province": "广西"},{"rooms": "3室2厅", "toward": "南北向", "year": "2014年建", "origin_url": "https://nn.esf.fang.com/chushou/3_164303077.htm", "unit": "10238元/㎡", "floor": "低层（共32层）", "address": "三塘-昆仑大道995号", "name": "嘉和城温莎北郡", "price": "\n\t\t\t\t\t\t\t\t\t\t\t86万", "city": "南宁", "area": "84㎡", "province": "广西"},{"rooms": "4室2厅", "toward": "南北向", "year": "2010年建", "origin_url": "https://nn.esf.fang.com/chushou/3_163172050.htm", "unit": "18487元/㎡", "floor": "低层（共32层）", "address": "凤岭北-荣和大地凤凰岭路1号(凤岭儿童公园旁)", "name": "荣和大地", "price": "\n\t\t\t\t\t\t\t\t\t\t\t220万", "city": "南宁", "area": "119㎡", "province": "广西"},{"rooms": "3室2厅", "toward": "南北向", "year": "2018年建", "origin_url": "https://nn.esf.fang.com/chushou/3_162347941.htm", "unit": "10101元/㎡", "floor": "中层（共32层）", "address": "新阳路-新阳路296-1号", "name": "天健城", "price": "\n\t\t\t\t\t\t\t\t\t\t\t100万", "city": "南宁", "area": "99㎡", "province": "广西"},{"rooms": "3室2厅", "toward": "南北向", "year": "2015年建", "origin_url": "https://nn.esf.fang.com/chushou/3_163710191.htm", "unit": "9659元/㎡", "floor": "中层（共28层）", "address": "新阳路-新阳路296-1号", "name": "天健城", "price": "\n\t\t\t\t\t\t\t\t\t\t\t85万", "city": "南宁", "area": "88㎡", "province": "广西"},{"rooms": "3室2厅", "toward": "南北向", "year": "2018年建", "origin_url": "https://nn.esf.fang.com/chushou/3_162347753.htm", "unit": "10000元/㎡", "floor": "中层（共32层）", "address": "新阳路-新阳路296-1号", "name": "天健城", "price": "\n\t\t\t\t\t\t\t\t\t\t\t93万", "city": "南宁", "area": "93㎡", "province": "广西"},{"rooms": "3室2厅", "toward": "南北向", "year": "2018年建", "origin_url": "https://nn.esf.fang.com/chushou/3_163027285.htm", "unit": "9615元/㎡", "floor": "低层（共33层）", "address": "沙井片区-江南大道、仁义段113号(清川大桥西侧)", "name": "中南春风南岸", "price": "\n\t\t\t\t\t\t\t\t\t\t\t75万", "city": "南宁", "area": "78㎡", "province": "广西"},{"rooms": "4室2厅", "toward": "南北向", "year": "2020年建", "origin_url": "https://nn.esf.fang.com/chushou/3_162831896.htm", "unit": "14495元/㎡", "floor": "高层（共32层）", "address": "东盟商务区-保利领秀前城", "name": "保利领秀前城", "price": "\n\t\t\t\t\t\t\t\t\t\t\t158万", "city": "南宁", "area": "109㎡", "province": "广西"},{"rooms": "3室2厅", "toward": "南向", "year": "2020年建", "origin_url": "https://nn.esf.fang.com/chushou/3_163043944.htm", "unit": "8941元/㎡", "floor": "低层（共33层）", "address": "沙井片区-仁和路55号(凤凰江畔)", "name": "荣和公园里", "price": "\n\t\t\t\t\t\t\t\t\t\t\t76万", "city": "南宁", "area": "85㎡", "province": "广西"},{"rooms": "4室2厅", "toward": "南北向", "year": "2015年建", "origin_url": "https://nn.esf.fang.com/chushou/3_163651085.htm", "unit": "16000元/㎡", "floor": "低层（共31层）", "address": "青秀山-华发国宾壹号荔滨大道6号(荔园山庄旁)", "name": "华发国宾壹号", "price": "\n\t\t\t\t\t\t\t\t\t\t\t200万", "city": "南宁", "area": "125㎡", "province": "广西"},{"rooms": "2室1厅", "toward": "南向", "year": "2020年建", "origin_url": "https://nn.esf.fang.com/chushou/3_162695997.htm", "unit": "10000元/㎡", "floor": "高层（共27层）", "address": "总部基地-平乐大道与歌海路交会处", "name": "五象世茂中心", "price": "\n\t\t\t\t\t\t\t\t\t\t\t48万", "city": "南宁", "area": "48㎡", "province": "广西"},{"rooms": "4室2厅", "toward": "南北向", "year": "2016年建", "origin_url": "https://nn.esf.fang.com/chushou/3_162465416.htm", "unit": "20979元/㎡", "floor": "中层（共41层）", "address": "凤岭北-荣和公园大道", "name": "荣和公园大道", "price": "\n\t\t\t\t\t\t\t\t\t\t\t300万", "city": "南宁", "area": "143㎡", "province": "广西"},{"rooms": "4室2厅", "toward": "南北向", "year": "2020年建", "origin_url": "https://nn.esf.fang.com/chushou/3_164170222.htm", "unit": "7986元/㎡", "floor": "中层（共18层）", "address": "邕宁周边-龙祥路38号(龙岗大道旁)", "name": "大唐盛世", "price": "\n\t\t\t\t\t\t\t\t\t\t\t115万", "city": "南宁", "area": "144㎡", "province": "广西"},{"rooms": "3室2厅", "toward": "南向", "year": "2020年建", "origin_url": "https://nn.esf.fang.com/chushou/3_164044414.htm", "unit": "11030元/㎡", "floor": "中层（共18层）", "address": "明秀东-明秀东路88号(明秀建材市场内)", "name": "荣和山水绿城", "price": "\n\t\t\t\t\t\t\t\t\t\t\t107万", "city": "南宁", "area": "97㎡", "province": "广西"},{"rooms": "3室2厅", "toward": "南向", "year": "2016年建", "origin_url": "https://nn.esf.fang.com/chushou/3_163124061.htm", "unit": "12681元/㎡", "floor": "中层（共32层）", "address": "龙岗新区-江湾路7号(龙岗大桥旁)", "name": "中国铁建江湾山语城", "price": "\n\t\t\t\t\t\t\t\t\t\t\t126万", "city": "南宁", "area": "99.36㎡", "province": "广西"},{"rooms": "3室2厅", "toward": "南北向", "year": "2015年建", "origin_url": "https://nn.esf.fang.com/chushou/3_163341291.htm", "unit": "16831元/㎡", "floor": "高层（共31层）", "address": "青秀山-华发国宾壹号荔滨大道6号(荔园山庄旁)", "name": "华发国宾壹号", "price": "\n\t\t\t\t\t\t\t\t\t\t\t170万", "city": "南宁", "area": "101㎡", "province": "广西"},{"rooms": "3室2厅", "toward": "南北向", "year": "2020年建", "origin_url": "https://nn.esf.fang.com/chushou/3_163637237.htm", "unit": "8679元/㎡", "floor": "高层（共15层）", "address": "大沙田片区-南宁市良庆区银海大道822号", "name": "国田秋月蓝湾", "price": "\n\t\t\t\t\t\t\t\t\t\t\t92万", "city": "南宁", "area": "106㎡", "province": "广西"},{"rooms": "5室2厅", "toward": "南向", "year": "2020年建", "origin_url": "https://nn.esf.fang.com/chushou/3_164179269.htm", "unit": "8642元/㎡", "floor": "中层（共26层）", "address": "龙岗新区-龙域香醍半岛", "name": "龙域香醍半岛", "price": "\n\t\t\t\t\t\t\t\t\t\t\t108.9万", "city": "南宁", "area": "126㎡", "province": "广西"},{"rooms": "3室2厅", "toward": "南北向", "year": "2016年建", "origin_url": "https://nn.esf.fang.com/chushou/3_164140180.htm", "unit": "14207元/㎡", "floor": "中层（共32层）", "address": "五象片区-五象大道体育中心东侧", "name": "天誉花园", "price": "\n\t\t\t\t\t\t\t\t\t\t\t130万", "city": "南宁", "area": "91.5㎡", "province": "广西"},{"rooms": "2室2厅", "toward": "南向", "year": "2020年建", "origin_url": "https://nn.esf.fang.com/chushou/3_163185279.htm", "unit": "8600元/㎡", "floor": "低层（共32层）", "address": "龙岗新区-那造路36号", "name": "银泉一品天誉", "price": "\n\t\t\t\t\t\t\t\t\t\t\t77.4万", "city": "南宁", "area": "90㎡", "province": "广西"},{"rooms": "2室2厅", "toward": "南北向", "year": "2020年建", "origin_url": "https://nn.esf.fang.com/chushou/3_163604752.htm", "unit": "8775元/㎡", "floor": "中层（共33层）", "address": "总部基地-平乐大道与歌海路交会处", "name": "五象世茂中心", "price": "\n\t\t\t\t\t\t\t\t\t\t\t43万", "city": "南宁", "area": "49㎡", "province": "广西"},{"rooms": "4室2厅", "toward": "南北向", "year": "2019年建", "origin_url": "https://nn.esf.fang.com/chushou/3_162691644.htm", "unit": "10365元/㎡", "floor": "高层（共11层）", "address": "东沟岭-邕武路20号(邕武路上3公里处)", "name": "保利山渐青", "price": "\n\t\t\t\t\t\t\t\t\t\t\t135万", "city": "南宁", "area": "130.24㎡", "province": "广西"},{"rooms": "4室2厅", "toward": "南北向", "year": "2017年建", "origin_url": "https://nn.esf.fang.com/chushou/3_163605657.htm", "unit": "18181元/㎡", "floor": "中层（共28层）", "address": "蟠龙片区-宋厢路18号(南宁艺术博物馆东畔)", "name": "盛科城", "price": "\n\t\t\t\t\t\t\t\t\t\t\t240万", "city": "南宁", "area": "132㎡", "province": "广西"},{"rooms": "4室2厅", "toward": "南北向", "year": "2015年建", "origin_url": "https://nn.esf.fang.com/chushou/3_163780947.htm", "unit": "10615元/㎡", "floor": "中层（共26层）", "address": "东沟岭-邕武路20号(邕武路上3公里处)", "name": "保利山渐青", "price": "\n\t\t\t\t\t\t\t\t\t\t\t138万", "city": "南宁", "area": "130㎡", "province": "广西"},{"rooms": "3室2厅", "toward": "南北向", "year": "2020年建", "origin_url": "https://nn.esf.fang.com/chushou/3_163989273.htm", "unit": "10090元/㎡", "floor": "中层（共30层）", "address": "凤岭北-合坡路18号", "name": "融创九熙府", "price": "\n\t\t\t\t\t\t\t\t\t\t\t88.8万", "city": "南宁", "area": "88㎡", "province": "广西"},{"rooms": "2室2厅", "toward": "南向", "year": "2009年建", "origin_url": "https://nn.esf.fang.com/chushou/3_164148388.htm", "unit": "16389元/㎡", "floor": "中层（共23层）", "address": "凤岭北-长湖路59号", "name": "香格里拉花园", "price": "\n\t\t\t\t\t\t\t\t\t\t\t138万", "city": "南宁", "area": "84.2㎡", "province": "广西"},{"rooms": "3室2厅", "toward": "南北向", "year": "2018年建", "origin_url": "https://nn.esf.fang.com/chushou/3_163170116.htm", "unit": "10576元/㎡", "floor": "中层（共26层）", "address": "北大路-华西路38号", "name": "大和平华西商业城住宅", "price": "\n\t\t\t\t\t\t\t\t\t\t\t98万", "city": "南宁", "area": "92.66㎡", "province": "广西"},{"rooms": "4室2厅", "floor": "低层（共34层）", "city": "南宁", "address": "凤岭北-荣和大地凤凰岭路1号(凤岭儿童公园旁)", "name": "荣和大地", "price": "\n\t\t\t\t\t\t\t\t\t\t\t235万", "toward": "南向", "origin_url": "https://nn.esf.fang.com/chushou/3_164325679.htm", "area": "119㎡", "province": "广西", "unit": "19747元/㎡"},{"rooms": "2室1厅", "toward": "南北向", "year": "2017年建", "origin_url": "https://nn.esf.fang.com/chushou/3_163356094.htm", "unit": "12000元/㎡", "floor": "低层（共33层）", "address": "龙岗新区-江湾路与永福路交汇处", "name": "南宁启迪东盟科技城", "price": "\n\t\t\t\t\t\t\t\t\t\t\t60万", "city": "南宁", "area": "50㎡", "province": "广西"},{"rooms": "3室2厅", "toward": "南北向", "year": "2020年建", "origin_url": "https://nn.esf.fang.com/chushou/3_164044381.htm", "unit": "10113元/㎡", "floor": "中层（共32层）", "address": "明秀东-明秀东路88号(明秀建材市场内)", "name": "荣和山水绿城", "price": "\n\t\t\t\t\t\t\t\t\t\t\t89万", "city": "南宁", "area": "88㎡", "province": "广西"},{"rooms": "4室2厅", "floor": "中层（共45层）", "city": "南宁", "address": "凤岭北-霖峰壹號", "name": "霖峰壹號", "price": "\n\t\t\t\t\t\t\t\t\t\t\t222万", "toward": "南向", "origin_url": "https://nn.esf.fang.com/chushou/3_163668568.htm", "area": "129㎡", "province": "广西", "unit": "17209元/㎡"},{"rooms": "4室2厅", "toward": "南北向", "year": "2020年建", "origin_url": "https://nn.esf.fang.com/chushou/3_163665874.htm", "unit": "9760元/㎡", "floor": "低层（共34层）", "address": "北湖路-南宁市北湖北路18号", "name": "昌泰尊府", "price": "\n\t\t\t\t\t\t\t\t\t\t\t122万", "city": "南宁", "area": "125㎡", "province": "广西"},{"rooms": "3室2厅", "toward": "南北向", "year": "2020年建", "origin_url": "https://nn.esf.fang.com/chushou/3_164052671.htm", "unit": "9139元/㎡", "floor": "低层（共32层）", "address": "沙井片区-定津路8号", "name": "奥园名门", "price": "\n\t\t\t\t\t\t\t\t\t\t\t85万", "city": "南宁", "area": "93㎡", "province": "广西"},{"rooms": "3室2厅", "toward": "东南向", "year": "2017年建", "origin_url": "https://nn.esf.fang.com/chushou/3_163681985.htm", "unit": "9500元/㎡", "floor": "中层（共30层）", "address": "良庆周边-那良路16号", "name": "印象愉景湾", "price": "\n\t\t\t\t\t\t\t\t\t\t\t80.75万", "city": "南宁", "area": "85㎡", "province": "广西"},{"rooms": "3室2厅", "toward": "南北向", "year": "2020年建", "origin_url": "https://nn.esf.fang.com/chushou/3_163519523.htm", "unit": "13144元/㎡", "floor": "低层（共34层）", "address": "凤岭北-万科城", "name": "万科城", "price": "\n\t\t\t\t\t\t\t\t\t\t\t127.5万", "city": "南宁", "area": "97㎡", "province": "广西"},{"city": "南宁", "address": "凤岭南-仙葫开发区蓉茉大道85号", "name": "龙胤花园一期", "price": "\n\t\t\t\t\t\t\t\t\t\t\t588.08万", "toward": "南向", "origin_url": "https://nn.esf.fang.com/chushou/10_164258100.htm", "area": "256.08㎡", "province": "广西", "unit": "22964元/㎡"},{"rooms": "5室2厅", "floor": "低层（共32层）", "city": "南宁", "address": "凤岭北-荣和大地凤凰岭路1号(凤岭儿童公园旁)", "name": "荣和大地", "price": "\n\t\t\t\t\t\t\t\t\t\t\t270万", "toward": "南北向", "origin_url": "https://nn.esf.fang.com/chushou/3_164073458.htm", "area": "141㎡", "province": "广西", "unit": "19148元/㎡"},{"rooms": "4室2厅", "toward": "南向", "year": "2011年建", "origin_url": "https://nn.esf.fang.com/chushou/3_162453804.htm", "unit": "11666元/㎡", "floor": "低层（共33层）", "address": "东葛片区-长湖路13号(长湖茶花园路口交汇处)", "name": "长湖景苑", "price": "\n\t\t\t\t\t\t\t\t\t\t\t210万", "city": "南宁", "area": "180㎡", "province": "广西"},{"rooms": "4室2厅", "toward": "南北向", "year": "2013年建", "origin_url": "https://nn.esf.fang.com/chushou/3_164029763.htm", "unit": "9147元/㎡", "floor": "中层（共30层）", "address": "三塘-昆仑大道995号", "name": "嘉和城温莎北郡", "price": "\n\t\t\t\t\t\t\t\t\t\t\t105万", "city": "南宁", "area": "114.79㎡", "province": "广西"},{"rooms": "4室2厅", "toward": "南北向", "year": "2020年建", "origin_url": "https://nn.esf.fang.com/chushou/3_164153580.htm", "unit": "7826元/㎡", "floor": "中层（共17层）", "address": "邕宁周边-龙祥路38号(龙岗大道旁)", "name": "大唐盛世", "price": "\n\t\t\t\t\t\t\t\t\t\t\t108万", "city": "南宁", "area": "138㎡", "province": "广西"},{"rooms": "4室2厅", "toward": "南北向", "year": "2020年建", "origin_url": "https://nn.esf.fang.com/chushou/3_163989106.htm", "unit": "10081元/㎡", "floor": "中层（共32层）", "address": "凤岭北-合坡路18号", "name": "融创九熙府", "price": "\n\t\t\t\t\t\t\t\t\t\t\t123万", "city": "南宁", "area": "122㎡", "province": "广西"},{"rooms": "3室2厅", "toward": "南向", "year": "2022年建", "origin_url": "https://nn.esf.fang.com/chushou/3_163029310.htm", "unit": "10909元/㎡", "floor": "中层（共30层）", "address": "白沙片区-白沙大道8号", "name": "凯旋1号上水湾", "price": "\n\t\t\t\t\t\t\t\t\t\t\t108万", "city": "南宁", "area": "99㎡", "province": "广西"},{"rooms": "3室2厅", "toward": "南北向", "year": "2017年建", "origin_url": "https://nn.esf.fang.com/chushou/3_163652019.htm", "unit": "8987元/㎡", "floor": "中层（共28层）", "address": "沙井片区-江南大道、仁义段113号(清川大桥西侧)", "name": "中南春风南岸", "price": "\n\t\t\t\t\t\t\t\t\t\t\t71万", "city": "南宁", "area": "79㎡", "province": "广西"},{"rooms": "3室2厅", "toward": "南北向", "year": "2017年建", "origin_url": "https://nn.esf.fang.com/chushou/3_164136010.htm", "unit": "10550元/㎡", "floor": "中层（共32层）", "address": "兴宁东-秀厢大道与金川路交汇处", "name": "南宁恒大华府", "price": "\n\t\t\t\t\t\t\t\t\t\t\t115万", "city": "南宁", "area": "109㎡", "province": "广西"},{"rooms": "3室2厅", "toward": "南向", "year": "2020年建", "origin_url": "https://nn.esf.fang.com/chushou/3_164294808.htm", "unit": "8059元/㎡", "floor": "中层（共22层）", "address": "相思湖新区-中梁柏仕公馆", "name": "中梁柏仕公馆", "price": "\n\t\t\t\t\t\t\t\t\t\t\t54万", "city": "南宁", "area": "67㎡", "province": "广西"},{"rooms": "2室2厅", "floor": "中层（共25层）", "city": "南宁", "address": "凤岭北-润华尚城街区民族大道199号", "name": "润华尚城街区", "price": "\n\t\t\t\t\t\t\t\t\t\t\t90万", "toward": "南向", "origin_url": "https://nn.esf.fang.com/chushou/3_164341018.htm", "area": "83.9㎡", "province": "广西", "unit": "10727元/㎡"},{"rooms": "3室2厅", "toward": "南向", "year": "2020年建", "origin_url": "https://nn.esf.fang.com/chushou/3_163945244.htm", "unit": "18976元/㎡", "floor": "高层（共32层）", "address": "凤岭北-凤凰岭路16号(即佛子岭路与凤凰岭路交汇处)", "name": "荣和公园大道", "price": "\n\t\t\t\t\t\t\t\t\t\t\t166.99万", "city": "南宁", "area": "88㎡", "province": "广西"},{"rooms": "4室2厅", "toward": "南北向", "year": "2020年建", "origin_url": "https://nn.esf.fang.com/chushou/3_163220134.htm", "unit": "9722元/㎡", "floor": "中层（共32层）", "address": "五一路片区-锦富路6号", "name": "锦上城", "price": "\n\t\t\t\t\t\t\t\t\t\t\t105万", "city": "南宁", "area": "108㎡", "province": "广西"},{"rooms": "3室2厅", "toward": "南北向", "year": "2017年建", "origin_url": "https://nn.esf.fang.com/chushou/3_163323075.htm", "unit": "9944元/㎡", "floor": "中层（共33层）", "address": "玉洞片区-凤凰路101号(玉洞小学旁)", "name": "阳光尚都", "price": "\n\t\t\t\t\t\t\t\t\t\t\t75万", "city": "南宁", "area": "75.42㎡", "province": "广西"},{"rooms": "3室2厅", "toward": "南向", "year": "2020年建", "origin_url": "https://nn.esf.fang.com/chushou/3_163855615.htm", "unit": "18651元/㎡", "floor": "中层（共32层）", "address": "凤岭北-凤凰岭路1号(凤岭儿童公园旁)", "name": "荣和大地", "price": "\n\t\t\t\t\t\t\t\t\t\t\t166万", "city": "南宁", "area": "89㎡", "province": "广西"},{"rooms": "3室2厅", "toward": "南向", "year": "2020年建", "origin_url": "https://nn.esf.fang.com/chushou/3_164214618.htm", "unit": "8080元/㎡", "floor": "低层（共28层）", "address": "大沙田片区-百灵路100号(英华桥南)", "name": "金悦澜湾", "price": "\n\t\t\t\t\t\t\t\t\t\t\t80万", "city": "南宁", "area": "99㎡", "province": "广西"},{"rooms": "3室2厅", "toward": "南北向", "year": "2020年建", "origin_url": "https://nn.esf.fang.com/chushou/3_163557005.htm", "unit": "8333元/㎡", "floor": "中层（共30层）", "address": "大沙田片区-百灵路100号(英华桥南)", "name": "金悦澜湾", "price": "\n\t\t\t\t\t\t\t\t\t\t\t90万", "city": "南宁", "area": "108㎡", "province": "广西"},{"rooms": "3室2厅", "toward": "南北向", "year": "2020年建", "origin_url": "https://nn.esf.fang.com/chushou/3_164084446.htm", "unit": "15747元/㎡", "floor": "高层（共15层）", "address": "蟠龙片区-玉凤路1号(龙堤中学门口正对面)", "name": "彰泰滨江学府", "price": "\n\t\t\t\t\t\t\t\t\t\t\t137万", "city": "南宁", "area": "87㎡", "province": "广西"},{"rooms": "3室2厅", "toward": "南北向", "year": "2020年建", "origin_url": "https://nn.esf.fang.com/chushou/3_164294698.htm", "unit": "7635元/㎡", "floor": "低层（共33层）", "address": "仙葫经济开发区-仙葫大道中25号", "name": "长岛溪山", "price": "\n\t\t\t\t\t\t\t\t\t\t\t68万", "city": "南宁", "area": "89.06㎡", "province": "广西"},{"rooms": "3室2厅", "toward": "南北向", "year": "2020年建", "origin_url": "https://nn.esf.fang.com/chushou/3_163076853.htm", "unit": "16991元/㎡", "floor": "中层（共32层）", "address": "蟠龙片区-宋厢路18号(南宁艺术博物馆东畔)", "name": "盛科城", "price": "\n\t\t\t\t\t\t\t\t\t\t\t209万", "city": "南宁", "area": "123㎡", "province": "广西"},{"rooms": "4室2厅", "toward": "南北向", "year": "2020年建", "origin_url": "https://nn.esf.fang.com/chushou/3_163819074.htm", "unit": "9433元/㎡", "floor": "中层（共32层）", "address": "五一片区-锦富路6号", "name": "锦上城", "price": "\n\t\t\t\t\t\t\t\t\t\t\t100万", "city": "南宁", "area": "106㎡", "province": "广西"},{"rooms": "4室2厅", "toward": "南北向", "year": "2020年建", "origin_url": "https://nn.esf.fang.com/chushou/3_163391122.htm", "unit": "20979元/㎡", "floor": "高层（共22层）", "address": "玉洞片区-南宁三中五象校区北门正对面", "name": "彰泰府", "price": "\n\t\t\t\t\t\t\t\t\t\t\t300万", "city": "南宁", "area": "143㎡", "province": "广西"},{"rooms": "4室2厅", "toward": "南北向", "year": "2019年建", "origin_url": "https://nn.esf.fang.com/chushou/3_163211513.htm", "unit": "19789元/㎡", "floor": "中层（共33层）", "address": "玉洞片区-平乐大道26号(平乐大道与凤凰路交会处)", "name": "龙光天瀛", "price": "\n\t\t\t\t\t\t\t\t\t\t\t188万", "city": "南宁", "area": "95㎡", "province": "广西"},{"city": "南宁", "address": "东盟商务区-东盟商务区铜鼓岭路8号", "name": "泰国城别墅", "price": "\n\t\t\t\t\t\t\t\t\t\t\t780万", "toward": "南向", "origin_url": "https://nn.esf.fang.com/chushou/10_164193017.htm", "area": "336㎡", "province": "广西", "unit": "23214元/㎡"},{"rooms": "4室2厅", "toward": "南北向", "year": "2020年建", "origin_url": "https://nn.esf.fang.com/chushou/3_163876687.htm", "unit": "9391元/㎡", "floor": "中层（共32层）", "address": "国家经济开发区-那洪大道37号(那洪壮锦路口)", "name": "汇东星城", "price": "\n\t\t\t\t\t\t\t\t\t\t\t108万", "city": "南宁", "area": "115㎡", "province": "广西"},{"rooms": "4室2厅", "toward": "南北向", "year": "2020年建", "origin_url": "https://nn.esf.fang.com/chushou/3_162691862.htm", "unit": "9846元/㎡", "floor": "高层（共20层）", "address": "东沟岭-邕武路20号(邕武路上3公里处)", "name": "保利山渐青", "price": "\n\t\t\t\t\t\t\t\t\t\t\t128万", "city": "南宁", "area": "130㎡", "province": "广西"},{"rooms": "4室2厅", "toward": "南向", "year": "2020年建", "origin_url": "https://nn.esf.fang.com/chushou/3_164182718.htm", "unit": "9182元/㎡", "floor": "中层（共31层）", "address": "白沙片区-友谊路东一里1-1号", "name": "阿尔卑斯", "price": "\n\t\t\t\t\t\t\t\t\t\t\t105.6万", "city": "南宁", "area": "115㎡", "province": "广西"}]
